{
  "date": "2026-07-03",
  "base": "KRW",
  "rates": {
    "USD": 0.00065,
    "INR": 0.06159,
    "PHP": 0.03976,
    "IDR": 11.635,
    "BRL": 0.00336,
    "TRY": 0.03015,
    "MXN": 0.01134,
    "AUD": 0.00094,
    "CAD": 0.00092,
    "DKK": 0.00423,
    "EUR": 0.00057,
    "GBP": 0.00049,
    "HKD": 0.00506,
    "JPY": 0.10433,
    "MYR": 0.00263,
    "NZD": 0.00114,
    "PLN": 0.00243,
    "SGD": 0.00084,
    "THB": 0.02151,
    "ZAR": 0.01057,
    "EGP": 0.031796,
    "NGN": 0.885634,
    "PKR": 0.179902,
    "TWD": 0.020711
  }
}
